pyfurc-0.2.4.dist-info/METADATA
pyfurc-0.2.4.dist-info/LICENSE
pyfurc-0.2.4.dist-info/RECORD
pyfurc-0.2.4.dist-info/WHEEL
pyfurc-0.2.4.dist-info/top_level.txt
pyfurc.ext/auto-07p/LICENSE
pyfurc.ext/auto-07p/lib/libauto.so
pyfurc.libs/libquadmath-96973f99.so.0.0.0
pyfurc.libs/libgfortran-040039e1.so.5.0.0
pyfurc/core.py
pyfurc/util.py
pyfurc/tools.py
pyfurc/__init__.py
