Metadata-Version: 2.1
Name: pyfurc
Version: 0.2.4
Summary: "AUTO-07p made accessible through python."
Home-page: https://github.com/klunkean/pyfurc
Author: klunkean
Author-email: klunkean@posteo.de
License: BSD-3-Clause
Project-URL: Documentation, https://pyfurc.readthedocs.io/
Classifier: License :: OSI Approved :: BSD License
Classifier: Programming Language :: Python :: 3
Classifier: Programming Language :: Python :: 3 :: Only
Classifier: Programming Language :: Python :: 3.8
Classifier: Programming Language :: Python :: 3.9
Classifier: Programming Language :: Python :: 3.10
Requires-Python: >=3.8
License-File: LICENSE
Requires-Dist: numpy
Requires-Dist: pandas
Requires-Dist: sympy
Provides-Extra: dev
Requires-Dist: black ; extra == 'dev'
Requires-Dist: bump2version ; extra == 'dev'
Requires-Dist: pre-commit ; extra == 'dev'
Requires-Dist: pytest ; extra == 'dev'
Provides-Extra: docs
Requires-Dist: jupyter-sphinx ; extra == 'docs'
Requires-Dist: pydata-sphinx-theme ; extra == 'docs'
Requires-Dist: sphinx ; extra == 'docs'
Requires-Dist: sphinx-lesson ; extra == 'docs'
Requires-Dist: sphinxcontrib-bibtex ; extra == 'docs'
Provides-Extra: test
Requires-Dist: pytest ; extra == 'test'
